dca/__init__.py
dca/__main__.py
dca/api.py
dca/hyper.py
dca/io.py
dca/layers.py
dca/loss.py
dca/network.py
dca/test.py
dca/train.py
dca/utils.py
DCA-0.3.4.dist-info/LICENSE.txt
DCA-0.3.4.dist-info/METADATA
DCA-0.3.4.dist-info/WHEEL
DCA-0.3.4.dist-info/entry_points.txt
DCA-0.3.4.dist-info/top_level.txt
DCA-0.3.4.dist-info/RECORD
