Metadata-Version: 2.1
Name: DCA
Version: 0.3.4
Summary: Count autoencoder for scRNA-seq denoising
Home-page: https://github.com/theislab/dca
Author: Gokcen Eraslan
Author-email: gokcen.eraslan@gmail.com
License: Apache License 2.0
Platform: UNKNOWN
Classifier: License :: OSI Approved :: Apache Software License
Classifier: Topic :: Scientific/Engineering :: Artificial Intelligence
Classifier: Programming Language :: Python :: 3.5
Requires-Dist: numpy (>=1.7)
Requires-Dist: keras (<2.6,>=2.4)
Requires-Dist: tensorflow (<2.5,>=2.0)
Requires-Dist: h5py
Requires-Dist: six (>=1.10.0)
Requires-Dist: scikit-learn
Requires-Dist: scanpy
Requires-Dist: kopt
Requires-Dist: pandas
